[
  {
    "source": "forbes.ua",
    "title": "РФ здійснила масований обстріл Одеси дронами: пошкоджено залізницю, є жертви (фото, відео)",
    "url": "https://forbes.ua/news/rf-zdiysnila-masovaniy-obstril-odesi-dronami-poshkodzheno-zaliznitsyu-e-zhertvi-foto-video-20062025-30686",
    "timestamp": "2025-06-20T06:24:39.629771Z"
  },
  {
    "source": "forbes.ua",
    "title": "Реальний ВВП України у травні зріс на 1,1% – ІЕД",
    "url": "https://forbes.ua/news/realniy-vvp-ukraini-u-travni-zris-na-11-ied-19062025-30678",
    "timestamp": "2025-06-20T06:24:39.629789Z"
  },
  {
    "source": "dou.ua",
    "title": "Розробка, DevOps та ШІ: українці можуть пройти безплатний IT-курс від Естонії",
    "url": "https://dou.ua/lenta/news/it-cuorse-for-beginners-estonia-java/?from=strichnews",
    "timestamp": "2025-06-20T06:24:43.121349Z"
  },
  {
    "source": "dou.ua",
    "title": "Кіберзахист від Гарварду, ШІ-тьютор і менеджмент: Prometheus відкрив безплатний курс",
    "url": "https://dou.ua/lenta/news/course-prometheus-cybersecurity-ai/?from=strichnews",
    "timestamp": "2025-06-20T06:24:43.121366Z"
  }
]