[
  {
    "source": "forbes.ua",
    "title": "Зеленський сформував делегацію для переговорів з США та РФ: очолює Єрмак, у складі Буданов, Умєров і Кислиця",
    "url": "https://forbes.ua/news/zelenskiy-sformuvav-delegatsiyu-dlya-peregovoriv-z-ssha-ta-rf-ocholyue-ermak-u-skladi-budanov-umerov-i-kislitsya-22112025-34338",
    "timestamp": "2025-11-23T06:24:04.090983Z"
  },
  {
    "source": "forbes.ua",
    "title": "Paramount Skydance, Comcast та Netflix офіційно подали пропозиції про поглинання Warner Bros. Discovery – CNBC",
    "url": "https://forbes.ua/news/paramount-skydance-comcast-ta-netflix-ofitsiyno-podali-propozitsii-pro-poglinannya-warner-bros-discovery-cnbc-21112025-34332",
    "timestamp": "2025-11-23T06:24:04.091000Z"
  },
  {
    "source": "dou.ua",
    "title": "650 інженерів та балістичні ракети. Що нового у Fire Point",
    "url": "https://dou.ua/lenta/news/fire-point-650-engineers/?from=strichnews",
    "timestamp": "2025-11-23T06:24:07.496457Z"
  },
  {
    "source": "dou.ua",
    "title": "Українська IT-компанія inVerita відкриває офіс у Колумбії. Кого шукають в команду",
    "url": "https://dou.ua/lenta/news/inverita-new-office/?from=strichnews",
    "timestamp": "2025-11-23T06:24:07.496470Z"
  }
]