[
  {
    "source": "forbes.ua",
    "title": "Росія вдарила по залізниці у Києві, поїзди курсують із затримками – УЗ",
    "url": "https://forbes.ua/news/rosiya-vdarila-po-zaliznitsi-u-kievi-poizdi-kursuyut-iz-zatrimkami-uz-04072025-31044",
    "timestamp": "2025-07-04T06:25:57.676460Z"
  },
  {
    "source": "forbes.ua",
    "title": "Перемога Трампа. Палата представників ухвалила «Один великий красивий закон»",
    "url": "https://forbes.ua/news/peremoga-trampa-palata-predstavnikiv-ukhvalila-velikiy-prekrasniy-zakonoproekt-03072025-31043",
    "timestamp": "2025-07-04T06:25:57.676478Z"
  },
  {
    "source": "dou.ua",
    "title": "Google відкрив в Україні доступ до ШІ-моделі Veo 3. Вона генерує відео зі звуком",
    "url": "https://dou.ua/lenta/news/google-launches-veo-3-in-ukraine/?from=strichnews",
    "timestamp": "2025-07-04T06:26:01.178948Z"
  },
  {
    "source": "dou.ua",
    "title": "Швейцарська SoftwareOne придбала норвезьку Crayon. Обидві мають офіси в Україні",
    "url": "https://dou.ua/lenta/news/softwareone-buys-crayon/?from=strichnews",
    "timestamp": "2025-07-04T06:26:01.178963Z"
  }
]