[
  {
    "source": "dou.ua",
    "title": "Українська компанія SKELAR відкриє офіс у Львові — у команду шукають ІТ-фахівців",
    "url": "https://dou.ua/lenta/news/skelar-office-in-lviv/?from=strichnews",
    "timestamp": "2026-05-24T08:25:05.670946Z"
  },
  {
    "source": "dou.ua",
    "title": "Уряд оновив правила бронювання для «критичних» підприємств — кого торкнуться зміни",
    "url": "https://dou.ua/lenta/news/rules-for-reserving-employees-changes/?from=strichnews",
    "timestamp": "2026-05-24T08:25:05.670965Z"
  }
]